README.md
setup.py
cron_lock/__init__.py
cron_lock/lock.py
cron_lock.egg-info/PKG-INFO
cron_lock.egg-info/SOURCES.txt
cron_lock.egg-info/dependency_links.txt
cron_lock.egg-info/requires.txt
cron_lock.egg-info/top_level.txt